.gitignore
README.rst
setup.py
js/__init__.py
js.d3.egg-info/PKG-INFO
js.d3.egg-info/SOURCES.txt
js.d3.egg-info/dependency_links.txt
js.d3.egg-info/entry_points.txt
js.d3.egg-info/namespace_packages.txt
js.d3.egg-info/not-zip-safe
js.d3.egg-info/requires.txt
js.d3.egg-info/top_level.txt
js/d3/__init__.py
js/d3/resources/d3.js
js/d3/resources/d3.min.js