Metadata-Version: 1.0
Name: js.d3
Version: 3.5.5
Summary: Fanstatic package for D3.js
Home-page: https://github.com/fanstatic/js.d3/
Author: Matt Good
Author-email: matt@matt-good.net
License: BSD
Platform: any
